soupwidget/__init__.py
soupwidget/widget.py
soupwidget-0.0.6.dist-info/METADATA
soupwidget-0.0.6.dist-info/WHEEL
soupwidget-0.0.6.dist-info/RECORD
