Metadata-Version: 2.1
Name: soupwidget
Version: 0.0.6
Summary: soupwidget
Author: Thiago César
Author-email: k1mbl3@gmail.com
Requires-Python: >=3.10,<4.0
Classifier: Programming Language :: Python :: 3
Classifier: Programming Language :: Python :: 3.10
Classifier: Programming Language :: Python :: 3.11
Requires-Dist: beautifulsoup4 (>=4.11.1,<5.0.0)
